monitor/WinPidUtil.py
monitor/__init__.py
monitor/get_process_name.py
monitor/mac_gpu.py
monitor/monitor_mac.py
monitor/monitor_mac_vmmap.py
monitor/monitor_pids.py
monitor/monitor_win.py
monitor/run_monitor.py
monitor/sys_info.py
monitor/DLL/GpuMonitorLib.dll
monitor/DLL/KernelBase.dll
monitor/DLL/LibreHardwareMonitorLib.dll
monitor/DLL/__init__.py
monitor/DLL/advapi32.dll
monitor/DLL/bcrypt.dll
monitor/DLL/kernel.appcore.dll
monitor/DLL/kernel32.dll
monitor/DLL/msvcirt.dll
monitor/DLL/msvcp140.dll
monitor/DLL/ntdll.dll
monitor/DLL/pdh.dll
monitor/DLL/rpcrt4.dll
monitor/DLL/sechost.dll
monitor/DLL/ucrtbased.dll
monitor/DLL/vcruntime140.dll
monitor/DLL/vcruntime140_1.dll
pmonitor-1.5.6.dist-info/METADATA
pmonitor-1.5.6.dist-info/WHEEL
pmonitor-1.5.6.dist-info/entry_points.txt
pmonitor-1.5.6.dist-info/top_level.txt
pmonitor-1.5.6.dist-info/RECORD
