Metadata-Version: 2.4
Name: pmonitor
Version: 1.5.6
Summary: pc monitor
Author: cfr
Author-email: 1354592998@qq.com
License: MIT
Platform: all
Requires-Python: >=3.6
Requires-Dist: PyLibreHardwareMonitor>=1.2.2
Requires-Dist: psutil>=5.9.8
Dynamic: author
Dynamic: author-email
Dynamic: description
Dynamic: license
Dynamic: platform
Dynamic: requires-dist
Dynamic: requires-python
Dynamic: summary
